llm_cost_estimation/__init__.py
llm_cost_estimation/count_tokens.py
llm_cost_estimation/estimate_cost.py
llm_cost_estimation/models.py
llm_cost_estimation-0.1.6.dist-info/LICENSE
llm_cost_estimation-0.1.6.dist-info/METADATA
llm_cost_estimation-0.1.6.dist-info/WHEEL
llm_cost_estimation-0.1.6.dist-info/RECORD
