Metadata-Version: 2.1
Name: llm_cost_estimation
Version: 0.1.6
Summary: A Python library for estimating the cost of LLM API calls
Author: Christopher Carroll Smith
Author-email: 75859865+chriscarrollsmith@users.noreply.github.com
Requires-Python: >=3.9,<4.0
Classifier: Programming Language :: Python :: 3
Classifier: Programming Language :: Python :: 3.9
Classifier: Programming Language :: Python :: 3.10
Classifier: Programming Language :: Python :: 3.11
Requires-Dist: tiktoken (>=0.4.0,<0.5.0)
